odoo/addons/sale_order_partner_restrict/README.rst
odoo/addons/sale_order_partner_restrict/__init__.py
odoo/addons/sale_order_partner_restrict/__manifest__.py
odoo/addons/sale_order_partner_restrict/i18n/sale_order_partner_restrict.pot
odoo/addons/sale_order_partner_restrict/models/__init__.py
odoo/addons/sale_order_partner_restrict/models/res_company.py
odoo/addons/sale_order_partner_restrict/models/res_config_settings.py
odoo/addons/sale_order_partner_restrict/models/sale.py
odoo/addons/sale_order_partner_restrict/readme/CONTRIBUTORS.rst
odoo/addons/sale_order_partner_restrict/readme/DESCRIPTION.rst
odoo/addons/sale_order_partner_restrict/readme/USAGE.rst
odoo/addons/sale_order_partner_restrict/static/description/icon.png
odoo/addons/sale_order_partner_restrict/static/description/index.html
odoo/addons/sale_order_partner_restrict/tests/__init__.py
odoo/addons/sale_order_partner_restrict/tests/test_sale_order_partner_restrict.py
odoo/addons/sale_order_partner_restrict/views/res_config_settings_views.xml
odoo/addons/sale_order_partner_restrict/views/sale_order_view.xml
odoo13_addon_sale_order_partner_restrict-13.0.1.0.1.dev4.dist-info/METADATA
odoo13_addon_sale_order_partner_restrict-13.0.1.0.1.dev4.dist-info/WHEEL
odoo13_addon_sale_order_partner_restrict-13.0.1.0.1.dev4.dist-info/top_level.txt
odoo13_addon_sale_order_partner_restrict-13.0.1.0.1.dev4.dist-info/RECORD
